.gitignore
README.rst
bootstrap.py
buildout.cfg
setup.cfg
setup.py
collective/__init__.py
collective.scss.egg-info/PKG-INFO
collective.scss.egg-info/SOURCES.txt
collective.scss.egg-info/dependency_links.txt
collective.scss.egg-info/entry_points.txt
collective.scss.egg-info/namespace_packages.txt
collective.scss.egg-info/not-zip-safe
collective.scss.egg-info/paster_plugins.txt
collective.scss.egg-info/requires.txt
collective.scss.egg-info/top_level.txt
collective/scss/__init__.py
collective/scss/configure.zcml
collective/scss/stylesheet.py
collective/scss/tests/__init__.py
collective/scss/tests/base.py
collective/scss/tests/layer.py
collective/scss/tests/test_stylesheet.py
collective/scss/tests/utils.py
collective/scss/tests/example/__init__.py
collective/scss/tests/example/configure.zcml
collective/scss/tests/example/mixins.scss
collective/scss/tests/example/nesting.scss
collective/scss/tests/example/selector-inheritance.scss
collective/scss/tests/example/variables.scss
docs/HISTORY.txt
docs/INSTALL.txt
docs/LICENSE.GPL
docs/LICENSE.txt