Metadata-Version: 1.0
Name: collective.scss
Version: 1.0b1
Summary: Integration of SCSS in the CMS Plone
Home-page: http://svn.plone.org/svn/collective/
Author: UNKNOWN
Author-email: UNKNOWN
License: GPL
Platform: UNKNOWN
Classifier: Framework :: Plone
Classifier: Programming Language :: Python
